{
    "os": "Linux-5.15.0-67-generic-x86_64-with-glibc2.10",
    "python": "3.8.8",
    "heartbeatAt": "2024-08-07T12:52:17.519897",
    "startedAt": "2024-08-07T12:52:16.019442",
    "docker": null,
    "cuda": null,
    "args": [
        "--local_rank=0",
        "--dataset",
        "ltcc",
        "--cfg",
        "configs/res50_cels_cal.yaml"
    ],
    "state": "running",
    "program": "main.py",
    "codePathLocal": "main.py",
    "codePath": "main.py",
    "host": "1370261e6f55",
    "username": "root",
    "executable": "/opt/conda/bin/python",
    "cpu_count": 20,
    "cpu_count_logical": 40,
    "cpu_freq": {
        "current": 1114.7447750000003,
        "min": 1000.0,
        "max": 3200.0
    },
    "cpu_freq_per_core": [
        {
            "current": 1000.008,
            "min": 1000.0,
            "max": 3200.0
        },
        {
            "current": 1000.019,
            "min": 1000.0,
            "max": 3200.0
        },
        {
            "current": 1000.302,
            "min": 1000.0,
            "max": 3200.0
        },
        {
            "current": 1000.762,
            "min": 1000.0,
            "max": 3200.0
        },
        {
            "current": 1000.589,
            "min": 1000.0,
            "max": 3200.0
        },
        {
            "current": 1000.038,
            "min": 1000.0,
            "max": 3200.0
        },
        {
            "current": 1000.685,
            "min": 1000.0,
            "max": 3200.0
        },
        {
            "current": 1001.675,
            "min": 1000.0,
            "max": 3200.0
        },
        {
            "current": 1000.319,
            "min": 1000.0,
            "max": 3200.0
        },
        {
            "current": 2898.335,
            "min": 1000.0,
            "max": 3200.0
        },
        {
            "current": 1000.52,
            "min": 1000.0,
            "max": 3200.0
        },
        {
            "current": 1130.315,
            "min": 1000.0,
            "max": 3200.0
        },
        {
            "current": 1000.328,
            "min": 1000.0,
            "max": 3200.0
        },
        {
            "current": 1000.188,
            "min": 1000.0,
            "max": 3200.0
        },
        {
            "current": 1001.106,
            "min": 1000.0,
            "max": 3200.0
        },
        {
            "current": 1000.724,
            "min": 1000.0,
            "max": 3200.0
        },
        {
            "current": 1000.897,
            "min": 1000.0,
            "max": 3200.0
        },
        {
            "current": 1000.693,
            "min": 1000.0,
            "max": 3200.0
        },
        {
            "current": 1000.45,
            "min": 1000.0,
            "max": 3200.0
        },
        {
            "current": 1000.388,
            "min": 1000.0,
            "max": 3200.0
        },
        {
            "current": 1000.584,
            "min": 1000.0,
            "max": 3200.0
        },
        {
            "current": 1000.981,
            "min": 1000.0,
            "max": 3200.0
        },
        {
            "current": 1000.535,
            "min": 1000.0,
            "max": 3200.0
        },
        {
            "current": 1000.255,
            "min": 1000.0,
            "max": 3200.0
        },
        {
            "current": 1000.156,
            "min": 1000.0,
            "max": 3200.0
        },
        {
            "current": 1000.77,
            "min": 1000.0,
            "max": 3200.0
        },
        {
            "current": 1000.015,
            "min": 1000.0,
            "max": 3200.0
        },
        {
            "current": 1000.107,
            "min": 1000.0,
            "max": 3200.0
        },
        {
            "current": 1000.602,
            "min": 1000.0,
            "max": 3200.0
        },
        {
            "current": 3057.957,
            "min": 1000.0,
            "max": 3200.0
        },
        {
            "current": 1000.628,
            "min": 1000.0,
            "max": 3200.0
        },
        {
            "current": 1001.102,
            "min": 1000.0,
            "max": 3200.0
        },
        {
            "current": 1000.082,
            "min": 1000.0,
            "max": 3200.0
        },
        {
            "current": 1000.309,
            "min": 1000.0,
            "max": 3200.0
        },
        {
            "current": 1001.41,
            "min": 1000.0,
            "max": 3200.0
        },
        {
            "current": 1000.261,
            "min": 1000.0,
            "max": 3200.0
        },
        {
            "current": 1000.251,
            "min": 1000.0,
            "max": 3200.0
        },
        {
            "current": 1001.22,
            "min": 1000.0,
            "max": 3200.0
        },
        {
            "current": 1000.337,
            "min": 1000.0,
            "max": 3200.0
        },
        {
            "current": 1000.729,
            "min": 1000.0,
            "max": 3200.0
        }
    ],
    "disk": {
        "/": {
            "total": 937.3305015563965,
            "used": 511.2320137023926
        }
    },
    "gpu": "NVIDIA TITAN RTX",
    "gpu_count": 2,
    "gpu_devices": [
        {
            "name": "NVIDIA TITAN RTX",
            "memory_total": 25769803776
        },
        {
            "name": "NVIDIA GeForce RTX 3090",
            "memory_total": 25769803776
        }
    ],
    "memory": {
        "total": 251.5177116394043
    }
}
